sbx_superlim/__init__.py
sbx_superlim/common.py
sbx_superlim/exporters.py
sbx_superlim/helpers.py
sbx_superlim/annotators/absabank_imm.py
sbx_superlim/annotators/argumentation_sent.py
sbx_superlim/annotators/dalaj_ged.py
sbx_superlim/annotators/swenli.py
sparv_sbx_superlim-0.1.0.dist-info/METADATA
sparv_sbx_superlim-0.1.0.dist-info/WHEEL
sparv_sbx_superlim-0.1.0.dist-info/entry_points.txt
sparv_sbx_superlim-0.1.0.dist-info/licenses/LICENSE
sparv_sbx_superlim-0.1.0.dist-info/RECORD
