Metadata-Version: 2.3
Name: sparv-sbx-superlim
Version: 0.1.0
Summary: A Sparv plugin for classifying text using the Superlim baseline models 
Author-email: Felix Morger <felix.morger@gu.se>
License: The GNU General Public License v3.0
Requires-Python: >=3.9
Requires-Dist: datasets~=2.20.0
Requires-Dist: sparv-pipeline~=5.0
Requires-Dist: transformers~=4.41.2
